setup.py
src/taprunner/__init__.py
src/unittest_tap_reporting.egg-info/PKG-INFO
src/unittest_tap_reporting.egg-info/SOURCES.txt
src/unittest_tap_reporting.egg-info/dependency_links.txt
src/unittest_tap_reporting.egg-info/top_level.txt