Metadata-Version: 1.1
Name: unittest-tap-reporting
Version: 0.2
Summary: PyUnit-based test runner with TAP reporting.
Home-page: http://github.com/vit1251/unittest-tap-reporting/tree/master/
Author: Vitold Sedyshev
Author-email: vit1251@gmail.com
License: LGPL
Keywords: pyunit,unittest,tap,jenkins,report,testrunner
Platform: Any
Classifier: Intended Audience :: Developers
Classifier: License :: OSI Approved :: GNU Library or Lesser General Public License (LGPL)
Classifier: Natural Language :: English
Classifier: Operating System :: OS Independent
Classifier: Programming Language :: Python
Classifier: Programming Language :: Python :: 2
Classifier: Topic :: Software Development :: Libraries :: Python Modules
Classifier: Topic :: Software Development :: Testing
